streamlit_toggle/__init__.py
streamlit_toggle/toggle.py
streamlit_toggle-0.1.2.dist-info/LICENSE
streamlit_toggle-0.1.2.dist-info/WHEEL
streamlit_toggle-0.1.2.dist-info/METADATA
streamlit_toggle-0.1.2.dist-info/RECORD
