Metadata-Version: 2.1
Name: streamlit-toggle
Version: 0.1.2
Summary: Toggling component for Streamlit
Home-page: https://st-toggle.streamlit.app
License: MIT
Author: Yi Zhang
Author-email: yizhang.dev@gmail.com
Requires-Python: >=3.7,<4.0
Classifier: License :: OSI Approved :: MIT License
Classifier: Programming Language :: Python :: 3
Classifier: Programming Language :: Python :: 3.7
Classifier: Programming Language :: Python :: 3.8
Classifier: Programming Language :: Python :: 3.9
Classifier: Programming Language :: Python :: 3.10
Classifier: Programming Language :: Python :: 3.11
Requires-Dist: streamlit (>=1.14.0,<2.0.0)
Requires-Dist: streamlit-space (>=0.1.4,<0.2.0)
Project-URL: Repository, https://github.com/imyizhang/streamlit-toggle
